{
	"info": {
		"_postman_id": "35aff4c1-3a62-4570-a466-3897d25c349a",
		"name": "OIL 25 26",
		"schema": "https://schema.getpostman.com/json/collection/v2.1.0/collection.json",
		"_exporter_id": "928748"
	},
	"item": [
		{
			"name": "Player Service",
			"item": [
				{
					"name": "Nominal",
					"item": [
						{
							"name": "1. Create Player Dany",
							"event": [
								{
									"listen": "test",
									"script": {
										"exec": [
											"pm.test(\"Status code is 201\", function () {",
											"    pm.response.to.have.status(201);",
											"});",
											"var jsonData = pm.response.json();",
											"pm.environment.set(\"playerId\", jsonData.id);",
											"pm.environment.set(\"playerPseudo\", jsonData.pseudo);"
										],
										"type": "text/javascript",
										"packages": {},
										"requests": {}
									}
								}
							],
							"request": {
								"method": "POST",
								"header": [
									{
										"key": "Content-Type",
										"value": "application/json",
										"type": "text"
									}
								],
								"body": {
									"mode": "raw",
									"raw": "{\n    \"pseudo\": \"Dany\",\n    \"score\": 1000\n}"
								},
								"url": {
									"raw": "{{baseUrl}}/api/players",
									"host": [
										"{{baseUrl}}"
									],
									"path": [
										"api",
										"players"
									]
								}
							},
							"response": []
						},
						{
							"name": "2. Get All Players",
							"event": [
								{
									"listen": "test",
									"script": {
										"exec": [
											"pm.test(\"Status code is 200\", function () {",
											"    pm.response.to.have.status(200);",
											"});"
										],
										"type": "text/javascript",
										"packages": {},
										"requests": {}
									}
								}
							],
							"request": {
								"method": "GET",
								"header": [],
								"url": {
									"raw": "{{baseUrl}}/api/players",
									"host": [
										"{{baseUrl}}"
									],
									"path": [
										"api",
										"players"
									]
								}
							},
							"response": []
						},
						{
							"name": "3. Get Player By Pseudo",
							"event": [
								{
									"listen": "test",
									"script": {
										"exec": [
											"pm.test(\"Status code is 200\", function () {",
											"    pm.response.to.have.status(200);",
											"});"
										],
										"type": "text/javascript",
										"packages": {},
										"requests": {}
									}
								}
							],
							"request": {
								"method": "GET",
								"header": [],
								"url": {
									"raw": "{{baseUrl}}/api/players/pseudo/{{playerPseudo}}",
									"host": [
										"{{baseUrl}}"
									],
									"path": [
										"api",
										"players",
										"pseudo",
										"{{playerPseudo}}"
									]
								}
							},
							"response": []
						},
						{
							"name": "4. Delete Player",
							"event": [
								{
									"listen": "test",
									"script": {
										"exec": [
											"pm.test(\"Status code is 204\", function () {",
											"    pm.response.to.have.status(204);",
											"});"
										],
										"type": "text/javascript",
										"packages": {},
										"requests": {}
									}
								}
							],
							"request": {
								"method": "DELETE",
								"header": [],
								"url": {
									"raw": "{{baseUrl}}/api/players/{{playerId}}",
									"host": [
										"{{baseUrl}}"
									],
									"path": [
										"api",
										"players",
										"{{playerId}}"
									]
								}
							},
							"response": []
						},
						{
							"name": "5. Get Player By ID (Verify Delete)",
							"event": [
								{
									"listen": "test",
									"script": {
										"exec": [
											"pm.test(\"Status code is 404\", function () {",
											"    pm.response.to.have.status(404);",
											"});"
										],
										"type": "text/javascript",
										"packages": {},
										"requests": {}
									}
								}
							],
							"request": {
								"method": "GET",
								"header": [],
								"url": {
									"raw": "{{baseUrl}}/api/players/{{playerId}}",
									"host": [
										"{{baseUrl}}"
									],
									"path": [
										"api",
										"players",
										"{{playerId}}"
									]
								}
							},
							"response": []
						}
					]
				},
				{
					"name": "Error Cases",
					"item": [
						{
							"name": "Get Unknown ID (404)",
							"event": [
								{
									"listen": "test",
									"script": {
										"exec": [
											"pm.test(\"Status code is 404\", function () {",
											"    pm.response.to.have.status(404);",
											"});",
											"pm.test(\"Error message check\", function () {",
											"    var jsonData = pm.response.json();",
											"    // Spring Boot default error structure usually has 'message' or 'error'",
											"    // Depending on configuration, checking status is often enough for basic tests",
											"});"
										],
										"type": "text/javascript",
										"packages": {},
										"requests": {}
									}
								}
							],
							"request": {
								"method": "GET",
								"header": [],
								"url": {
									"raw": "{{baseUrl}}/api/players/999999",
									"host": [
										"{{baseUrl}}"
									],
									"path": [
										"api",
										"players",
										"999999"
									]
								}
							},
							"response": []
						},
						{
							"name": "Delete Unknown ID (404)",
							"event": [
								{
									"listen": "test",
									"script": {
										"exec": [
											"pm.test(\"Status code is 404\", function () {",
											"    pm.response.to.have.status(404);",
											"});"
										],
										"type": "text/javascript",
										"packages": {},
										"requests": {}
									}
								}
							],
							"request": {
								"method": "DELETE",
								"header": [],
								"url": {
									"raw": "{{baseUrl}}/api/players/999999",
									"host": [
										"{{baseUrl}}"
									],
									"path": [
										"api",
										"players",
										"999999"
									]
								}
							},
							"response": []
						},
						{
							"name": "Get Unknown Pseudo (404)",
							"event": [
								{
									"listen": "test",
									"script": {
										"exec": [
											"pm.test(\"Status code is 404\", function () {",
											"    pm.response.to.have.status(404);",
											"});"
										],
										"type": "text/javascript",
										"packages": {},
										"requests": {}
									}
								}
							],
							"request": {
								"method": "GET",
								"header": [],
								"url": {
									"raw": "{{baseUrl}}/api/players/pseudo/UnknownPlayerXYZ",
									"host": [
										"{{baseUrl}}"
									],
									"path": [
										"api",
										"players",
										"pseudo",
										"UnknownPlayerXYZ"
									]
								}
							},
							"response": []
						}
					]
				}
			]
		}
	]
}